{
    "os": "Linux-5.4.0-137-generic-x86_64-with-glibc2.31",
    "python": "3.9.12",
    "heartbeatAt": "2024-01-31T03:57:04.782019",
    "startedAt": "2024-01-31T03:57:04.401716",
    "docker": null,
    "cuda": null,
    "args": [],
    "state": "running",
    "program": "/juice2/scr2/nanditan/commvqa/idefics/eval_idefics.py",
    "codePathLocal": "eval_idefics.py",
    "codePath": "idefics/eval_idefics.py",
    "git": {
        "remote": "https://github.com/nnaik39/commvqa.git",
        "commit": "5c0f8cef9e095832b404fd0250735920678e3243"
    },
    "email": null,
    "root": "/juice2/scr2/nanditan/commvqa",
    "host": "jagupard35.stanford.edu",
    "username": "nanditan",
    "executable": "/nlp/scr/nanditan/miniconda3/bin/python3",
    "cpu_count": 48,
    "cpu_count_logical": 96,
    "cpu_freq": {
        "current": 1825.9623854166668,
        "min": 1500.0,
        "max": 2850.0
    },
    "cpu_freq_per_core": [
        {
            "current": 3997.319,
            "min": 1500.0,
            "max": 2850.0
        },
        {
            "current": 3191.773,
            "min": 1500.0,
            "max": 2850.0
        },
        {
            "current": 3219.623,
            "min": 1500.0,
            "max": 2850.0
        },
        {
            "current": 3211.864,
            "min": 1500.0,
            "max": 2850.0
        },
        {
            "current": 3216.292,
            "min": 1500.0,
            "max": 2850.0
        },
        {
            "current": 3205.88,
            "min": 1500.0,
            "max": 2850.0
        },
        {
            "current": 1496.664,
            "min": 1500.0,
            "max": 2850.0
        },
        {
            "current": 1496.856,
            "min": 1500.0,
            "max": 2850.0
        },
        {
            "current": 1496.584,
            "min": 1500.0,
            "max": 2850.0
        },
        {
            "current": 1496.806,
            "min": 1500.0,
            "max": 2850.0
        },
        {
            "current": 1497.277,
            "min": 1500.0,
            "max": 2850.0
        },
        {
            "current": 1496.639,
            "min": 1500.0,
            "max": 2850.0
        },
        {
            "current": 3214.159,
            "min": 1500.0,
            "max": 2850.0
        },
        {
            "current": 2899.726,
            "min": 1500.0,
            "max": 2850.0
        },
        {
            "current": 3118.329,
            "min": 1500.0,
            "max": 2850.0
        },
        {
            "current": 3114.672,
            "min": 1500.0,
            "max": 2850.0
        },
        {
            "current": 3998.042,
            "min": 1500.0,
            "max": 2850.0
        },
        {
            "current": 3998.045,
            "min": 1500.0,
            "max": 2850.0
        },
        {
            "current": 1497.009,
            "min": 1500.0,
            "max": 2850.0
        },
        {
            "current": 1496.811,
            "min": 1500.0,
            "max": 2850.0
        },
        {
            "current": 1496.92,
            "min": 1500.0,
            "max": 2850.0
        },
        {
            "current": 1495.41,
            "min": 1500.0,
            "max": 2850.0
        },
        {
            "current": 1496.299,
            "min": 1500.0,
            "max": 2850.0
        },
        {
            "current": 1496.135,
            "min": 1500.0,
            "max": 2850.0
        },
        {
            "current": 1498.875,
            "min": 1500.0,
            "max": 2850.0
        },
        {
            "current": 1495.878,
            "min": 1500.0,
            "max": 2850.0
        },
        {
            "current": 1499.033,
            "min": 1500.0,
            "max": 2850.0
        },
        {
            "current": 1497.084,
            "min": 1500.0,
            "max": 2850.0
        },
        {
            "current": 1496.991,
            "min": 1500.0,
            "max": 2850.0
        },
        {
            "current": 1496.544,
            "min": 1500.0,
            "max": 2850.0
        },
        {
            "current": 1496.883,
            "min": 1500.0,
            "max": 2850.0
        },
        {
            "current": 1497.83,
            "min": 1500.0,
            "max": 2850.0
        },
        {
            "current": 1497.346,
            "min": 1500.0,
            "max": 2850.0
        },
        {
            "current": 1497.29,
            "min": 1500.0,
            "max": 2850.0
        },
        {
            "current": 1496.941,
            "min": 1500.0,
            "max": 2850.0
        },
        {
            "current": 1497.238,
            "min": 1500.0,
            "max": 2850.0
        },
        {
            "current": 1497.855,
            "min": 1500.0,
            "max": 2850.0
        },
        {
            "current": 1497.163,
            "min": 1500.0,
            "max": 2850.0
        },
        {
            "current": 1496.999,
            "min": 1500.0,
            "max": 2850.0
        },
        {
            "current": 1498.743,
            "min": 1500.0,
            "max": 2850.0
        },
        {
            "current": 1496.171,
            "min": 1500.0,
            "max": 2850.0
        },
        {
            "current": 1497.157,
            "min": 1500.0,
            "max": 2850.0
        },
        {
            "current": 1498.852,
            "min": 1500.0,
            "max": 2850.0
        },
        {
            "current": 1497.568,
            "min": 1500.0,
            "max": 2850.0
        },
        {
            "current": 1497.086,
            "min": 1500.0,
            "max": 2850.0
        },
        {
            "current": 1496.145,
            "min": 1500.0,
            "max": 2850.0
        },
        {
            "current": 1496.992,
            "min": 1500.0,
            "max": 2850.0
        },
        {
            "current": 1496.364,
            "min": 1500.0,
            "max": 2850.0
        },
        {
            "current": 3900.286,
            "min": 1500.0,
            "max": 2850.0
        },
        {
            "current": 3109.59,
            "min": 1500.0,
            "max": 2850.0
        },
        {
            "current": 3110.877,
            "min": 1500.0,
            "max": 2850.0
        },
        {
            "current": 3107.889,
            "min": 1500.0,
            "max": 2850.0
        },
        {
            "current": 3108.935,
            "min": 1500.0,
            "max": 2850.0
        },
        {
            "current": 3118.641,
            "min": 1500.0,
            "max": 2850.0
        },
        {
            "current": 1498.785,
            "min": 1500.0,
            "max": 2850.0
        },
        {
            "current": 1494.341,
            "min": 1500.0,
            "max": 2850.0
        },
        {
            "current": 1497.307,
            "min": 1500.0,
            "max": 2850.0
        },
        {
            "current": 1497.034,
            "min": 1500.0,
            "max": 2850.0
        },
        {
            "current": 1496.312,
            "min": 1500.0,
            "max": 2850.0
        },
        {
            "current": 1493.128,
            "min": 1500.0,
            "max": 2850.0
        },
        {
            "current": 3116.288,
            "min": 1500.0,
            "max": 2850.0
        },
        {
            "current": 3111.692,
            "min": 1500.0,
            "max": 2850.0
        },
        {
            "current": 3113.265,
            "min": 1500.0,
            "max": 2850.0
        },
        {
            "current": 3104.937,
            "min": 1500.0,
            "max": 2850.0
        },
        {
            "current": 3990.938,
            "min": 1500.0,
            "max": 2850.0
        },
        {
            "current": 3990.776,
            "min": 1500.0,
            "max": 2850.0
        },
        {
            "current": 1496.353,
            "min": 1500.0,
            "max": 2850.0
        },
        {
            "current": 1495.538,
            "min": 1500.0,
            "max": 2850.0
        },
        {
            "current": 1497.624,
            "min": 1500.0,
            "max": 2850.0
        },
        {
            "current": 1497.343,
            "min": 1500.0,
            "max": 2850.0
        },
        {
            "current": 1496.27,
            "min": 1500.0,
            "max": 2850.0
        },
        {
            "current": 1495.317,
            "min": 1500.0,
            "max": 2850.0
        },
        {
            "current": 1497.173,
            "min": 1500.0,
            "max": 2850.0
        },
        {
            "current": 1495.145,
            "min": 1500.0,
            "max": 2850.0
        },
        {
            "current": 1494.175,
            "min": 1500.0,
            "max": 2850.0
        },
        {
            "current": 1495.617,
            "min": 1500.0,
            "max": 2850.0
        },
        {
            "current": 1497.534,
            "min": 1500.0,
            "max": 2850.0
        },
        {
            "current": 1497.949,
            "min": 1500.0,
            "max": 2850.0
        },
        {
            "current": 1496.842,
            "min": 1500.0,
            "max": 2850.0
        },
        {
            "current": 1496.825,
            "min": 1500.0,
            "max": 2850.0
        },
        {
            "current": 1491.901,
            "min": 1500.0,
            "max": 2850.0
        },
        {
            "current": 1496.655,
            "min": 1500.0,
            "max": 2850.0
        },
        {
            "current": 1496.883,
            "min": 1500.0,
            "max": 2850.0
        },
        {
            "current": 1499.482,
            "min": 1500.0,
            "max": 2850.0
        },
        {
            "current": 1497.227,
            "min": 1500.0,
            "max": 2850.0
        },
        {
            "current": 1495.839,
            "min": 1500.0,
            "max": 2850.0
        },
        {
            "current": 1497.027,
            "min": 1500.0,
            "max": 2850.0
        },
        {
            "current": 1497.864,
            "min": 1500.0,
            "max": 2850.0
        },
        {
            "current": 1495.556,
            "min": 1500.0,
            "max": 2850.0
        },
        {
            "current": 1498.672,
            "min": 1500.0,
            "max": 2850.0
        },
        {
            "current": 1497.855,
            "min": 1500.0,
            "max": 2850.0
        },
        {
            "current": 1497.264,
            "min": 1500.0,
            "max": 2850.0
        },
        {
            "current": 1493.895,
            "min": 1500.0,
            "max": 2850.0
        },
        {
            "current": 1497.035,
            "min": 1500.0,
            "max": 2850.0
        },
        {
            "current": 1496.471,
            "min": 1500.0,
            "max": 2850.0
        },
        {
            "current": 1498.163,
            "min": 1500.0,
            "max": 2850.0
        }
    ],
    "disk": {
        "/": {
            "total": 218.87727737426758,
            "used": 158.4156379699707
        }
    },
    "gpu": "NVIDIA RTX A6000",
    "gpu_count": 1,
    "gpu_devices": [
        {
            "name": "NVIDIA RTX A6000",
            "memory_total": 51527024640
        }
    ],
    "memory": {
        "total": 503.7493896484375
    }
}
